wagtailstatic/__init__.py
wagtailstatic/apps.py
wagtailstatic/decorators.py
wagtailstatic/local_files.py
wagtailstatic/s3.py
wagtailstatic/signals.py
wagtailstatic/wagtail_hooks.py
wagtailstatic/management/__init__.py
wagtailstatic/management/commands/__init__.py
wagtailstatic/management/commands/generate_local_tree.py
wagtailstatic/management/commands/upload_site_tree.py
wagtail_static-0.0.4.dist-info/METADATA
wagtail_static-0.0.4.dist-info/WHEEL
wagtail_static-0.0.4.dist-info/top_level.txt
wagtail_static-0.0.4.dist-info/RECORD
